_mir.cpython-39-darwin.so
mir/__init__.py
mir_python-0.3.1.dist-info/licenses/LICENSE
mir_python-0.3.1.dist-info/METADATA
mir_python-0.3.1.dist-info/WHEEL
mir_python-0.3.1.dist-info/top_level.txt
mir_python-0.3.1.dist-info/RECORD
